{
  "headers": {
    "content-type": "application/typescript; charset=utf-8",
    "x-amz-replication-status": "COMPLETED",
    "x-cache": "Hit from cloudfront",
    "date": "Wed, 20 Dec 2023 01:10:23 GMT",
    "strict-transport-security": "max-age=63072000; includeSubDomains; preload",
    "via": "http/2 edgeproxy-h",
    "x-amz-cf-id": "KSklinZZ77Yw4iP_PYpnxQ1XnoqyQO8fHrc6xwyrnp8JsdcAJY3eTg==",
    "last-modified": "Fri, 25 Mar 2022 13:32:50 GMT",
    "accept-ranges": "bytes",
    "cache-control": "public, max-age=31536000, immutable",
    "server": "deno/gcp-europe-west3",
    "cross-origin-embedder-policy": "same-origin",
    "x-amz-version-id": "7I89Xd2wt4Z8v3iHvlBn.kr8d97L2dDe",
    "access-control-allow-origin": "*",
    "x-frame-options": "DENY",
    "server-timing": "fetchSource;dur=4",
    "referrer-policy": "strict-origin-when-cross-origin",
    "content-length": "354364",
    "cross-origin-opener-policy": "same-origin",
    "cross-origin-resource-policy": "same-origin",
    "age": "27324190",
    "etag": "\"5946a1144e5e60ddc8eb782f10ac6d3a\"",
    "vary": "Accept-Encoding, Origin",
    "x-amz-cf-pop": "FRA56-P5",
    "x-content-type-options": "nosniff",
    "content-security-policy": "default-src 'none'; style-src 'unsafe-inline'; sandbox"
  },
  "url": "https://deno.land/std@0.132.0/node/internal_binding/_winerror.ts",
  "now": {
    "secs_since_epoch": 1730358814,
    "nanos_since_epoch": 645210624
  }
}